redact_proxy_reid/__init__.py
redact_proxy_reid/anthropic_wrapper.py
redact_proxy_reid/auth.py
redact_proxy_reid/gemini_wrapper.py
redact_proxy_reid/models.py
redact_proxy_reid/openai_wrapper.py
redact_proxy_reid/reidentifier.py
redact_proxy_reid/tokenizer.py
redact_proxy_reid-0.1.2.dist-info/METADATA
redact_proxy_reid-0.1.2.dist-info/WHEEL
redact_proxy_reid-0.1.2.dist-info/RECORD
