Metadata-Version: 2.4
Name: redact-proxy-reid
Version: 0.1.2
Summary: DE-ID/RE-ID SDK for LLMs - Full-cycle PHI protection with automatic re-identification
Project-URL: Homepage, https://redact.health
Project-URL: Product Page, https://www.redact.health/redact-proxy-reid
Project-URL: Repository, https://github.com/cspergel/redact-proxy-reid
Project-URL: Issues, https://github.com/cspergel/redact-proxy-reid/issues
Author-email: Craig Spergel <cspergel@gmail.com>
License-Expression: LicenseRef-Commercial
Keywords: anthropic,de-identification,healthcare,hipaa,llm,openai,phi,re-identification,redaction
Classifier: Development Status :: 4 - Beta
Classifier: Intended Audience :: Developers
Classifier: Intended Audience :: Healthcare Industry
Classifier: Programming Language :: Python :: 3
Classifier: Programming Language :: Python :: 3.9
Classifier: Programming Language :: Python :: 3.10
Classifier: Programming Language :: Python :: 3.11
Classifier: Programming Language :: Python :: 3.12
Classifier: Topic :: Scientific/Engineering :: Artificial Intelligence
Classifier: Topic :: Security
Requires-Python: >=3.9
Requires-Dist: cryptography>=41.0.0
Requires-Dist: httpx>=0.25.0
Requires-Dist: pydantic>=2.0.0
Requires-Dist: redact-proxy>=0.1.5
Provides-Extra: all
Requires-Dist: anthropic>=0.18.0; extra == 'all'
Requires-Dist: google-generativeai>=0.4.0; extra == 'all'
Requires-Dist: openai>=1.0.0; extra == 'all'
Provides-Extra: anthropic
Requires-Dist: anthropic>=0.18.0; extra == 'anthropic'
Provides-Extra: dev
Requires-Dist: pytest-asyncio>=0.21.0; extra == 'dev'
Requires-Dist: pytest>=7.0.0; extra == 'dev'
Provides-Extra: gemini
Requires-Dist: google-generativeai>=0.4.0; extra == 'gemini'
Provides-Extra: openai
Requires-Dist: openai>=1.0.0; extra == 'openai'
